{
  "$schema": "https://json-schema.org/draft/2020-12/schema",
  "description": "Version history for station data",
  "station_id": "07MA004",
  "versions": [
    {
      "semantic_tag": "v1.0.0",
      "timestamp": "2026-02-11T17:18:04.858420",
      "data_source": "WSC_basins",
      "polygon_file": "07MA004_polygon_v1.0.0.geojson",
      "source_metadata": {
        "StationNum": "07MA004",
        "NameNom": "WILLIAM RIVER ABOVE CARSWELL RIVER",
        "Status": "discontinued",
        "Etat": "ferm\u00e9e",
        "Area_km2": "4060.61",
        "Aire_km2": "4060.61",
        "Version": "Prerelease/Pr\u00e9liminaire",
        "Date": "2021-12-17"
      }
    },
    {
      "semantic_tag": "v1.1.0",
      "timestamp": "2026-02-11T17:19:30.700025",
      "data_source": "HYDAT_polygons",
      "polygon_file": "07MA004_polygon_v1.1.0.geojson",
      "source_metadata": {
        "StationNum": "07MA004",
        "NameNom": "WILLIAM RIVER ABOVE CARSWELL RIVER",
        "Status": "discontinued",
        "Etat": "ferm\u00e9e",
        "Area_km2": 4075.55,
        "Aire_km2": 4075.55,
        "Remark": null,
        "Remarque": null,
        "Version": "June 2024 / juin 2024",
        "Date_rev": "2024-06-01",
        "Shape_Leng": 729960.0,
        "Shape_Area": 4075551900.0
      }
    }
  ],
  "schema_version": "1.0.0",
  "current_version": "v1.1.0",
  "version_count": 2,
  "first_committed": "2026-02-11T17:18:04.858420",
  "last_updated": "2026-02-11T17:19:30.700025",
  "comparisons": {
    "v1.0.0_vs_v1.1.0": {
      "computed_at": "2026-02-11T17:19:30.700025",
      "jaccard_index": 0.9945,
      "old_area_km2": 4060.6101,
      "new_area_km2": 4075.5508,
      "absolute_area_diff_km2": 14.9407,
      "percent_area_diff": 0.37
    }
  }
}